pack_legolas_lee_package0/__init__.py
pack_legolas_lee_package0/my_funcs.py
pack_legolas_lee_package0-1.0.dist-info/METADATA
pack_legolas_lee_package0-1.0.dist-info/WHEEL
pack_legolas_lee_package0-1.0.dist-info/top_level.txt
pack_legolas_lee_package0-1.0.dist-info/RECORD
