Metadata-Version: 2.1
Name: pack-legolas-lee-package0
Version: 1.0
Summary: My First Package
Author: Legolas
Author-email: jingui.ljg@alibaba-inc.com
Classifier: Programming Language :: Python :: 3
Classifier: License :: OSI Approved :: MIT License
Classifier: Operating System :: OS Independent
